[{"1. open":"12.1500","2. high":"12.1800","3. low":"11.0300","4. close":"11.0400","5. volume":"4733000"},{"1. open":"12.6100","2. high":"13.5200","3. low":"11.8200","4. close":"12.0200","5. volume":"32830200"},{"1. open":"10.5900","2. high":"13.0400","3. low":"10.0500","4. close":"12.4600","5. volume":"35280500"},{"1. open":"11.1300","2. high":"12.7700","3. low":"10.1200","4. close":"10.3100","5. volume":"49689600"},{"1. open":"13.0600","2. high":"13.3000","3. low":"10.7700","4. close":"11.1400","5. volume":"39377900"},{"1. open":"14.9500","2. high":"14.9500","3. low":"12.5100","4. close":"13.0000","5. volume":"41031100"},{"1. open":"11.3000","2. high":"15.3000","3. low":"11.0700","4. close":"14.7800","5. volume":"87948500"},{"1. open":"7.0600","2. high":"11.8300","3. low":"6.9700","4. close":"11.0600","5. volume":"71010300"},{"1. open":"6.4000","2. high":"7.5900","3. low":"5.0600","4. close":"7.0600","5. volume":"51063400"},{"1. open":"5.8800","2. high":"7.6500","3. low":"5.0900","4. close":"6.7400","5. volume":"62596400"},{"1. open":"14.3400","2. high":"15.2000","3. low":"5.6000","4. close":"6.1100","5. volume":"79365900"},{"1. open":"16.6600","2. high":"18.1300","3. low":"13.4500","4. close":"14.3400","5. volume":"31887700"},{"1. open":"15.4200","2. high":"19.3500","3. low":"15.4000","4. close":"16.7300","5. volume":"47362200"},{"1. open":"12.5500","2. high":"15.6500","3. low":"12.0600","4. close":"15.5600","5. volume":"30011500"},{"1. open":"12.3500","2. high":"13.5200","3. low":"11.9700","4. close":"12.5000","5. volume":"36179000"},{"1. open":"10.5000","2. high":"12.2700","3. low":"10.0200","4. close":"12.1900","5. volume":"48232900"},{"1. open":"11.5000","2. high":"11.8200","3. low":"9.7200","4. close":"10.5000","5. volume":"54992500"},{"1. open":"9.8300","2. high":"11.5900","3. low":"9.6300","4. close":"11.3200","5. volume":"48753800"},{"1. open":"8.4200","2. high":"10.0000","3. low":"8.1400","4. close":"9.8000","5. volume":"40656800"},{"1. open":"6.9000","2. high":"8.4600","3. low":"6.8700","4. close":"8.3000","5. volume":"29225900"},{"1. open":"6.5000","2. high":"6.9000","3. low":"5.9200","4. close":"6.9000","5. volume":"20265600"},{"1. open":"6.0200","2. high":"6.6000","3. low":"5.6600","4. close":"6.5100","5. volume":"20477600"},{"1. open":"6.0000","2. high":"6.6900","3. low":"5.7200","4. close":"6.0000","5. volume":"18943200"},{"1. open":"6.7700","2. high":"6.8500","3. low":"5.7600","4. close":"5.9700","5. volume":"20953600"},{"1. open":"6.0000","2. high":"6.9700","3. low":"5.9500","4. close":"6.7300","5. volume":"23621400"},{"1. open":"5.1800","2. high":"6.2000","3. low":"5.0100","4. close":"6.0000","5. volume":"26113000"},{"1. open":"4.8100","2. high":"5.3800","3. low":"4.3900","4. close":"5.1500","5. volume":"22646700"},{"1. open":"3.0600","2. high":"5.0200","3. low":"2.9900","4. close":"4.7900","5. volume":"27302500"},{"1. open":"3.4700","2. high":"3.5000","3. low":"2.9200","4. close":"3.0500","5. volume":"10213400"},{"1. open":"3.7600","2. high":"4.0700","3. low":"3.4000","4. close":"3.4700","5. volume":"13854100"},{"1. open":"3.6500","2. high":"4.3200","3. low":"3.6100","4. close":"3.7200","5. volume":"14680500"},{"1. open":"4.2600","2. high":"4.4400","3. low":"3.5300","4. close":"3.6500","5. volume":"15927900"},{"1. open":"4.5400","2. high":"4.8800","3. low":"3.9800","4. close":"4.1900","5. volume":"16780700"},{"1. open":"5.0500","2. high":"5.1000","3. low":"4.2500","4. close":"4.5300","5. volume":"21699000"},{"1. open":"6.0100","2. high":"6.2600","3. low":"4.9400","4. close":"5.2300","5. volume":"16184200"},{"1. open":"6.2500","2. high":"6.3600","3. low":"5.5400","4. close":"6.0500","5. volume":"11367300"},{"1. open":"5.7200","2. high":"6.4800","3. low":"5.5300","4. close":"6.2500","5. volume":"20532400"},{"1. open":"4.9700","2. high":"5.7400","3. low":"4.8800","4. close":"5.7400","5. volume":"11822200"},{"1. open":"5.4800","2. high":"5.4800","3. low":"4.7400","4. close":"4.9600","5. volume":"16356500"},{"1. open":"5.5700","2. high":"6.0500","3. low":"5.1400","4. close":"5.4000","5. volume":"15242600"},{"1. open":"4.8100","2. high":"6.1300","3. low":"4.7500","4. close":"5.5500","5. volume":"20695500"},{"1. open":"4.5900","2. high":"4.9900","3. low":"4.4200","4. close":"4.7700","5. volume":"19251900"},{"1. open":"3.9500","2. high":"4.6600","3. low":"3.9300","4. close":"4.5800","5. volume":"17191300"},{"1. open":"3.8000","2. high":"3.9900","3. low":"3.6900","4. close":"3.9500","5. volume":"14808300"},{"1. open":"4.4400","2. high":"4.7800","3. low":"3.6500","4. close":"3.7500","5. volume":"27072200"},{"1. open":"4.6200","2. high":"4.8000","3. low":"4.2600","4. close":"4.4400","5. volume":"21306900"},{"1. open":"5.1000","2. high":"5.1900","3. low":"4.4500","4. close":"4.6000","5. volume":"19933000"},{"1. open":"4.5100","2. high":"5.4800","3. low":"4.5100","4. close":"5.0500","5. volume":"23339100"},{"1. open":"3.7000","2. high":"4.6400","3. low":"3.6300","4. close":"4.4900","5. volume":"23565700"},{"1. open":"3.9800","2. high":"4.0300","3. low":"3.3900","4. close":"3.7000","5. volume":"13203900"},{"1. open":"4.4400","2. high":"4.5400","3. low":"3.7400","4. close":"3.9800","5. volume":"23666500"},{"1. open":"3.8500","2. high":"4.5100","3. low":"3.7800","4. close":"4.4400","5. volume":"12461700"},{"1. open":"4.2500","2. high":"4.4600","3. low":"3.7900","4. close":"3.8400","5. volume":"11328500"},{"1. open":"4.6900","2. high":"4.8800","3. low":"4.1500","4. close":"4.2100","5. volume":"18707400"},{"1. open":"3.8500","2. high":"4.6400","3. low":"3.7900","4. close":"4.6200","5. volume":"24078100"},{"1. open":"4.0200","2. high":"4.3000","3. low":"3.6600","4. close":"3.8400","5. volume":"16958400"},{"1. open":"3.6900","2. high":"4.2600","3. low":"3.5200","4. close":"4.0300","5. volume":"19684200"},{"1. open":"4.0800","2. high":"4.3100","3. low":"3.6000","4. close":"3.6600","5. volume":"24726900"},{"1. open":"4.5700","2. high":"4.9900","3. low":"4.0900","4. close":"4.1600","5. volume":"24170300"},{"1. open":"4.1200","2. high":"4.7400","3. low":"4.1000","4. close":"4.5400","5. volume":"15190900"},{"1. open":"4.1000","2. high":"4.2600","3. low":"3.8000","4. close":"4.1300","5. volume":"25450900"},{"1. open":"4.1000","2. high":"4.3200","3. low":"3.8300","4. close":"4.1200","5. volume":"18601200"},{"1. open":"4.0000","2. high":"4.3900","3. low":"3.8300","4. close":"4.0800","5. volume":"20141900"},{"1. open":"3.4500","2. high":"4.3700","3. low":"3.4200","4. close":"4.0000","5. volume":"31064000"},{"1. open":"3.4200","2. high":"3.8300","3. low":"3.2000","4. close":"3.4400","5. volume":"43527700"},{"1. open":"2.9200","2. high":"3.4900","3. low":"2.8100","4. close":"3.4900","5. volume":"36451400"},{"1. open":"3.3100","2. high":"3.3500","3. low":"2.7200","4. close":"2.9200","5. volume":"60206800"},{"1. open":"3.7700","2. high":"3.8800","3. low":"3.2500","4. close":"3.3000","5. volume":"44699500"},{"1. open":"4.7000","2. high":"4.7500","3. low":"3.7500","4. close":"3.7700","5. volume":"62365000"},{"1. open":"4.4500","2. high":"5.2400","3. low":"4.3600","4. close":"4.9600","5. volume":"55877000"},{"1. open":"4.5800","2. high":"4.8400","3. low":"4.1300","4. close":"4.4200","5. volume":"59009600"},{"1. open":"4.3600","2. high":"4.6600","3. low":"4.0600","4. close":"4.5900","5. volume":"53114400"},{"1. open":"5.4400","2. high":"5.4400","3. low":"4.3000","4. close":"4.3300","5. volume":"53133600"},{"1. open":"5.7200","2. high":"5.8800","3. low":"4.9700","4. close":"5.4400","5. volume":"39328900"},{"1. open":"5.3700","2. high":"6.0400","3. low":"4.6800","4. close":"5.8000","5. volume":"37766800"},{"1. open":"5.3800","2. high":"6.0900","3. low":"4.4400","4. close":"5.3600","5. volume":"61195900"},{"1. open":"6.7900","2. high":"7.0700","3. low":"5.3200","4. close":"5.4500","5. volume":"47011800"},{"1. open":"6.2800","2. high":"6.8800","3. low":"5.8000","4. close":"6.7700","5. volume":"42633400"},{"1. open":"6.5800","2. high":"6.7500","3. low":"6.0500","4. close":"6.2400","5. volume":"42631300"},{"1. open":"6.8000","2. high":"7.1300","3. low":"6.3600","4. close":"6.5500","5. volume":"44913400"},{"1. open":"7.1700","2. high":"7.6900","3. low":"6.6500","4. close":"6.8000","5. volume":"33261800"},{"1. open":"7.6800","2. high":"7.8500","3. low":"7.0400","4. close":"7.1800","5. volume":"36447300"},{"1. open":"7.3000","2. high":"7.7000","3. low":"6.6300","4. close":"7.6000","5. volume":"33297400"},{"1. open":"7.1600","2. high":"7.5000","3. low":"6.6800","4. close":"7.1400","5. volume":"45252200"},{"1. open":"8.1400","2. high":"8.2400","3. low":"7.0000","4. close":"7.1600","5. volume":"54018700"},{"1. open":"8.1800","2. high":"8.3100","3. low":"7.6800","4. close":"8.1500","5. volume":"32253600"},{"1. open":"8.3400","2. high":"8.4900","3. low":"7.7600","4. close":"8.2200","5. volume":"31274500"},{"1. open":"8.4100","2. high":"9.0500","3. low":"8.1200","4. close":"8.3500","5. volume":"45544800"},{"1. open":"8.0500","2. high":"9.0000","3. low":"8.0400","4. close":"8.4400","5. volume":"37582400"},{"1. open":"8.5500","2. high":"8.8500","3. low":"7.4500","4. close":"8.0100","5. volume":"41848600"},{"1. open":"7.9500","2. high":"8.6500","3. low":"7.0100","4. close":"8.4900","5. volume":"51117400"},{"1. open":"8.3000","2. high":"8.8000","3. low":"7.1100","4. close":"7.8800","5. volume":"63473400"},{"1. open":"9.3700","2. high":"9.5300","3. low":"8.3000","4. close":"8.3000","5. volume":"75871000"},{"1. open":"9.7900","2. high":"10.0700","3. low":"8.9400","4. close":"9.4500","5. volume":"41862100"},{"1. open":"9.9600","2. high":"10.1400","3. low":"9.0100","4. close":"9.8000","5. volume":"35502500"},{"1. open":"9.7700","2. high":"10.6400","3. low":"9.4800","4. close":"10.0000","5. volume":"40465200"},{"1. open":"9.5000","2. high":"9.8900","3. low":"9.1000","4. close":"9.7700","5. volume":"38753700"},{"1. open":"8.5800","2. high":"9.4600","3. low":"8.4900","4. close":"9.4000","5. volume":"46578900"},{"1. open":"8.0500","2. high":"8.8000","3. low":"7.8500","4. close":"8.6100","5. volume":"38794500"},{"1. open":"7.9000","2. high":"8.4800","3. low":"7.5300","4. close":"8.1000","5. volume":"33867000"},{"1. open":"7.7100","2. high":"8.0600","3. low":"7.3300","4. close":"7.8100","5. volume":"36509500"},{"1. open":"6.4600","2. high":"7.7300","3. low":"6.3900","4. close":"7.7000","5. volume":"44570300"},{"1. open":"6.8400","2. high":"7.0500","3. low":"5.7700","4. close":"6.5500","5. volume":"41105500"},{"1. open":"6.4500","2. high":"6.9500","3. low":"5.8000","4. close":"6.8400","5. volume":"32376100"},{"1. open":"7.2700","2. high":"7.8300","3. low":"6.2500","4. close":"6.6400","5. volume":"56533500"},{"1. open":"6.9900","2. high":"7.6500","3. low":"6.8500","4. close":"7.1300","5. volume":"47442300"},{"1. open":"7.5200","2. high":"8.1800","3. low":"6.8600","4. close":"7.0300","5. volume":"34771200"},{"1. open":"7.2300","2. high":"8.0100","3. low":"7.0600","4. close":"7.4700","5. volume":"40563200"},{"1. open":"6.1200","2. high":"7.5000","3. low":"5.9700","4. close":"7.2000","5. volume":"45886700"},{"1. open":"6.6000","2. high":"7.1100","3. low":"5.8400","4. close":"6.1800","5. volume":"25774742"},{"1. open":"6.1900","2. high":"6.6800","3. low":"5.7400","4. close":"6.5000","5. volume":"21909251"},{"1. open":"5.2800","2. high":"6.7000","3. low":"5.0200","4. close":"6.3900","5. volume":"24988126"},{"1. open":"7.0500","2. high":"7.4900","3. low":"5.2400","4. close":"5.3500","5. volume":"31433892"},{"1. open":"7.7900","2. high":"7.7900","3. low":"5.6200","4. close":"6.9300","5. volume":"34306254"},{"1. open":"7.9100","2. high":"8.0500","3. low":"7.1900","4. close":"7.5900","5. volume":"29182309"},{"1. open":"8.6000","2. high":"8.8600","3. low":"7.8400","4. close":"7.8800","5. volume":"23546681"},{"1. open":"8.6100","2. high":"8.6100","3. low":"7.8000","4. close":"8.6000","5. volume":"23380660"},{"1. open":"8.4400","2. high":"9.1800","3. low":"8.2000","4. close":"8.6500","5. volume":"33638251"},{"1. open":"7.5000","2. high":"8.4900","3. low":"7.3600","4. close":"8.4200","5. volume":"28010005"},{"1. open":"7.9200","2. high":"8.0600","3. low":"7.1800","4. close":"7.5000","5. volume":"25517508"},{"1. open":"8.6300","2. high":"8.8900","3. low":"7.5800","4. close":"7.9000","5. volume":"26309252"},{"1. open":"9.0500","2. high":"9.0700","3. low":"7.9300","4. close":"8.6000","5. volume":"31775896"},{"1. open":"9.6800","2. high":"10.1100","3. low":"8.3400","4. close":"8.9600","5. volume":"30914316"},{"1. open":"8.8100","2. high":"10.1100","3. low":"8.7300","4. close":"9.6800","5. volume":"58446008"},{"1. open":"8.4000","2. high":"8.9700","3. low":"8.2000","4. close":"8.8200","5. volume":"18618323"},{"1. open":"8.2900","2. high":"8.5000","3. low":"7.6500","4. close":"8.2400","5. volume":"16120885"},{"1. open":"6.8000","2. high":"8.3300","3. low":"6.4200","4. close":"8.1900","5. volume":"17537904"},{"1. open":"6.4000","2. high":"7.3300","3. low":"6.4000","4. close":"6.7100","5. volume":"15735874"},{"1. open":"6.0700","2. high":"6.6400","3. low":"5.0600","4. close":"6.6000","5. volume":"23296882"},{"1. open":"6.8900","2. high":"6.9300","3. low":"5.8600","4. close":"6.0600","5. volume":"37007124"},{"1. open":"7.4900","2. high":"7.9000","3. low":"6.4700","4. close":"6.6000","5. volume":"5385033"},{"1. open":"7.6500","2. high":"7.6500","3. low":"6.2000","4. close":"7.5000","5. volume":"4879773"},{"1. open":"8.5000","2. high":"8.5700","3. low":"7.2100","4. close":"7.5500","5. volume":"6828012"},{"1. open":"7.8900","2. high":"8.7500","3. low":"7.8300","4. close":"8.5400","5. volume":"7782309"},{"1. open":"6.1000","2. high":"7.8000","3. low":"6.0700","4. close":"7.8000","5. volume":"9787658"},{"1. open":"6.7500","2. high":"7.4000","3. low":"5.4500","4. close":"6.1600","5. volume":"13369830"},{"1. open":"7.0000","2. high":"7.0000","3. low":"6.3300","4. close":"6.8000","5. volume":"28119307"},{"1. open":"5.8500","2. high":"7.2500","3. low":"5.1500","4. close":"6.8200","5. volume":"6926980"},{"1. open":"3.3700","2. high":"6.1800","3. low":"3.3700","4. close":"5.7700","5. volume":"6887293"},{"1. open":"3.3000","2. high":"3.4300","3. low":"3.0000","4. close":"3.3600","5. volume":"6685977"},{"1. open":"3.6200","2. high":"3.9700","3. low":"3.0500","4. close":"3.2900","5. volume":"4399993"},{"1. open":"2.4500","2. high":"3.5800","3. low":"2.4500","4. close":"3.5200","5. volume":"3000885"},{"1. open":"2.0000","2. high":"2.5700","3. low":"1.9400","4. close":"2.4900","5. volume":"5093741"},{"1. open":"2.3500","2. high":"2.6100","3. low":"1.9600","4. close":"2.0000","5. volume":"3665943"},{"1. open":"2.9500","2. high":"3.4500","3. low":"2.3500","4. close":"2.3700","5. volume":"4598510"},{"1. open":"2.3000","2. high":"3.3000","3. low":"2.0900","4. close":"2.9000","5. volume":"5695265"},{"1. open":"2.7900","2. high":"3.0900","3. low":"1.9700","4. close":"2.3500","5. volume":"2459044"},{"1. open":"4.0300","2. high":"4.0300","3. low":"2.6400","4. close":"2.7900","5. volume":"6623145"},{"1. open":"5.5700","2. high":"5.8600","3. low":"3.3000","4. close":"4.0000","5. volume":"11059704"},{"1. open":"7.7900","2. high":"7.7900","3. low":"5.1000","4. close":"5.5700","5. volume":"2486011"},{"1. open":"8.9500","2. high":"8.9900","3. low":"6.9500","4. close":"7.8000","5. volume":"5393089"},{"1. open":"11.8500","2. high":"11.9900","3. low":"8.6000","4. close":"9.2500","5. volume":"4514988"},{"1. open":"10.6000","2. high":"12.4900","3. low":"10.6000","4. close":"11.7900","5. volume":"4004045"},{"1. open":"10.1200","2. high":"10.6000","3. low":"9.0500","4. close":"10.5500","5. volume":"5549811"},{"1. open":"13.3900","2. high":"13.5500","3. low":"9.5200","4. close":"10.1000","5. volume":"4967655"},{"1. open":"12.3100","2. high":"15.2100","3. low":"11.6500","4. close":"13.1900","5. volume":"3284144"},{"1. open":"16.9000","2. high":"17.5000","3. low":"10.0000","4. close":"12.3900","5. volume":"4859522"},{"1. open":"15.2500","2. high":"17.0000","3. low":"13.8000","4. close":"16.9000","5. volume":"4264737"},{"1. open":"15.7500","2. high":"17.6100","3. low":"13.0000","4. close":"15.2500","5. volume":"7262715"},{"1. open":"17.3400","2. high":"18.2000","3. low":"14.3500","4. close":"15.7500","5. volume":"7184799"},{"1. open":"15.4000","2. high":"17.8500","3. low":"14.5000","4. close":"17.3400","5. volume":"3253277"},{"1. open":"16.6000","2. high":"17.3500","3. low":"13.4000","4. close":"15.0000","5. volume":"8968114"},{"1. open":"17.2000","2. high":"20.4000","3. low":"15.9900","4. close":"16.6000","5. volume":"6121419"},{"1. open":"15.6000","2. high":"17.6900","3. low":"15.1000","4. close":"17.2000","5. volume":"6735115"},{"1. open":"13.3200","2. high":"17.3000","3. low":"13.0000","4. close":"15.6500","5. volume":"8281633"}]